llama_index/readers/pdf_table/__init__.py
llama_index/readers/pdf_table/base.py
llama_index_readers_pdf_table-0.4.1.dist-info/METADATA
llama_index_readers_pdf_table-0.4.1.dist-info/WHEEL
llama_index_readers_pdf_table-0.4.1.dist-info/licenses/LICENSE
llama_index_readers_pdf_table-0.4.1.dist-info/RECORD
