Metadata-Version: 2.4
Name: llama-index-readers-pdf-table
Version: 0.4.1
Summary: llama-index readers pdf_table integration
Author-email: Your Name <you@example.com>
Maintainer: yy0867
License-Expression: GPL-3.0-or-later
License-File: LICENSE
Keywords: pdf,pdf table,table
Requires-Python: <4.0,>=3.9
Requires-Dist: camelot-py<0.12,>=0.11.0
Requires-Dist: ghostscript<0.8,>=0.7
Requires-Dist: llama-index-core<0.15,>=0.13.0
Requires-Dist: opencv-python<5,>=4.9.0.80
Requires-Dist: pandas
